statuspageio/__init__.py
statuspageio/client.py
statuspageio/configuration.py
statuspageio/errors.py
statuspageio/http_client.py
statuspageio/services.py
crunch_statuspageio-0.7.dist-info/METADATA
crunch_statuspageio-0.7.dist-info/WHEEL
crunch_statuspageio-0.7.dist-info/RECORD
